openvisioncapsule_tools/__init__.py
openvisioncapsule_tools/bulk_accuracy/bulk_test_main.py
openvisioncapsule_tools/bulk_accuracy/capsule_accuracy_common.py
openvisioncapsule_tools/bulk_accuracy/capsule_accuracy_event_loop.py
openvisioncapsule_tools/bulk_accuracy/capsule_accuracy_report.py
openvisioncapsule_tools/bulk_accuracy/capsule_mgmt_basic.py
openvisioncapsule_tools/bulk_accuracy/capsule_mgmt_local.py
openvisioncapsule_tools/bulk_accuracy/capsule_mgmt_remote.py
openvisioncapsule_tools/bulk_testing.sh
openvisioncapsule_tools/capsule_benchmark/README.md
openvisioncapsule_tools/capsule_benchmark/args.py
openvisioncapsule_tools/capsule_benchmark/benchmarking.py
openvisioncapsule_tools/capsule_benchmark/capsules.py
openvisioncapsule_tools/capsule_benchmark/main.py
openvisioncapsule_tools/capsule_benchmark/output.py
openvisioncapsule_tools/capsule_benchmark/requirements.txt
openvisioncapsule_tools/capsule_benchmark/workers.py
openvisioncapsule_tools/capsule_classifier_accuracy/capsule_classifier_accuracy.py
openvisioncapsule_tools/capsule_classifier_accuracy/detect_videos.py
openvisioncapsule_tools/capsule_infer/__init__.py
openvisioncapsule_tools/capsule_infer/capsule_infer.py
openvisioncapsule_tools/capsule_infer/capsule_inference.py
openvisioncapsule_tools/capsule_packaging/__init__.py
openvisioncapsule_tools/capsule_packaging/capsule_packaging.py
openvisioncapsule_tools/cli.py
openvisioncapsule_tools/command_utils.py
openvisioncapsule_tools/devices/__init__.py
openvisioncapsule_tools/devices/devices.py
openvisioncapsule_tools/devices/openvino_loading_test.py
openvisioncapsule_tools/options.json
openvisioncapsule_tools/print_module_info.py
openvisioncapsule_tools/print_utils.py
openvisioncapsule_tools/translations/portal.en.yml
openvisioncapsule_tools-0.5.4.dist-info/METADATA
openvisioncapsule_tools-0.5.4.dist-info/WHEEL
openvisioncapsule_tools-0.5.4.dist-info/entry_points.txt
openvisioncapsule_tools-0.5.4.dist-info/RECORD
