Metadata-Version: 2.1
Name: openvisioncapsule-tools
Version: 0.5.4
Summary: A tool to help users to package, test OpenVisionCapsules
License: BSD License
Author: Stephen Li
Author-email: stephen@aotu.ai
Requires-Python: >=3.8,<4.0
Classifier: License :: OSI Approved :: BSD License
Classifier: License :: Other/Proprietary License
Classifier: Programming Language :: Python
Classifier: Programming Language :: Python :: 3
Classifier: Programming Language :: Python :: 3.8
Classifier: Programming Language :: Python :: 3.9
Classifier: Programming Language :: Python :: 3.10
Classifier: Programming Language :: Python :: 3.11
Classifier: Programming Language :: Python :: 3.12
Classifier: Programming Language :: Python :: 3.13
Requires-Dist: Cython (==0.29.30)
Requires-Dist: Pillow (>=7.0.0)
Requires-Dist: PyYAML (>=6.0.2,<7.0.0)
Requires-Dist: matplotlib (==3.5.1)
Requires-Dist: numpy (>=1.19.2,<1.20.0)
Requires-Dist: opencv_contrib_python
Requires-Dist: opencv_contrib_python_headless
Requires-Dist: openvino (>=2024.1.0,<2024.5.0)
Requires-Dist: pandas (>=1.1.5,<2.0.0)
Requires-Dist: python_i18n (>=0.3.9,<0.4.0)
Requires-Dist: setuptools (==73.0.1)
Requires-Dist: tools (==0.1.9)
Requires-Dist: torch (==1.9.0)
Requires-Dist: tqdm (==4.54.1)
Requires-Dist: vcap (>=0.5.2)
